hldlib/__init__.py
hldlib/hldbasics.py
hldlib/hlddirections.py
hldlib/hlderror.py
hldlib/hldlevel.py
hldlib/hldobjects.py
hldlib/hldsavefile.py
hldlib/hldtype.py
hldlib-0.1.2.dist-info/METADATA
hldlib-0.1.2.dist-info/WHEEL
hldlib-0.1.2.dist-info/RECORD
